kid_sdk/__init__.py
kid_sdk/client.py
kid_sdk/config.py
kid_sdk/utils.py
kid_sdk/kid_profile/__init__.py
kid_sdk/kid_profile/apps.py
kid_sdk/kid_profile/manager.py
kid_sdk/kid_profile/mixin.py
kid_sdk/kid_profile/models.py
kid_sdk/kid_profile/routers.py
kid_sdk/kid_profile/migrations/0001_initial.py
kid_sdk/kid_profile/migrations/__init__.py
kid_sdk-1.2.dist-info/METADATA
kid_sdk-1.2.dist-info/WHEEL
kid_sdk-1.2.dist-info/top_level.txt
kid_sdk-1.2.dist-info/RECORD
