Metadata-Version: 2.4
Name: kid_sdk
Version: 1.2
Author: Zonesmart
Author-email: e.beliakov@dev.kokoc.com
Requires-Dist: authlib
Requires-Dist: requests
Requires-Dist: pendulum
Dynamic: author
Dynamic: author-email
Dynamic: requires-dist
